chatways/__init__.py
chatways/cli.py
chatways/log.py
chatways/registry.py
chatways/bot/__init__.py
chatways/bot/chat_with_arxiv.py
chatways/bot/simple_chat.py
chatways/bot/utils.py
chatways/llm/__init__.py
chatways/llm/fake.py
chatways/llm/huggingface.py
chatways/llm/openai.py
chatways/llm/openmind.py
chatways/llm/utils.py
chatways/template/chat_comparison.py
chatways/template/chat_with_arxiv.py
chatways/template/simple_chat.py
chatways/tool/__init__.py
chatways/tool/arxiv.py
chatways/tool/utils.py
chatways-0.1.0.dev5.dist-info/LICENSE
chatways-0.1.0.dev5.dist-info/METADATA
chatways-0.1.0.dev5.dist-info/WHEEL
chatways-0.1.0.dev5.dist-info/entry_points.txt
chatways-0.1.0.dev5.dist-info/top_level.txt
chatways-0.1.0.dev5.dist-info/RECORD
