Metadata-Version: 2.1
Name: chatways
Version: 0.1.0.dev5
Summary: Chatways
Home-page: https://github.com/zhangsibo1129/chatways
Author: Sibo Zhang
Author-email: zhangsibo1129@gmail.com
Classifier: Programming Language :: Python :: 3
Classifier: License :: OSI Approved :: MIT License
Classifier: Operating System :: OS Independent
Requires-Python: >=3.8
License-File: LICENSE
Requires-Dist: gradio
Requires-Dist: transformers
Requires-Dist: openai
Requires-Dist: sentencepiece
Requires-Dist: protobuf
Requires-Dist: accelerate
